mcp_pdf/__init__.py
mcp_pdf/security.py
mcp_pdf/server.py
mcp_pdf/server_legacy.py
mcp_pdf/server_refactored.py
mcp_pdf/mixins/__init__.py
mcp_pdf/mixins/advanced_forms.py
mcp_pdf/mixins/annotations.py
mcp_pdf/mixins/base.py
mcp_pdf/mixins/document_analysis.py
mcp_pdf/mixins/document_assembly.py
mcp_pdf/mixins/document_processing.py
mcp_pdf/mixins/form_management.py
mcp_pdf/mixins/image_processing.py
mcp_pdf/mixins/security_analysis.py
mcp_pdf/mixins/stubs.py
mcp_pdf/mixins/table_extraction.py
mcp_pdf/mixins/text_extraction.py
mcp_pdf/mixins_official/__init__.py
mcp_pdf/mixins_official/advanced_forms.py
mcp_pdf/mixins_official/annotations.py
mcp_pdf/mixins_official/content_analysis.py
mcp_pdf/mixins_official/document_analysis.py
mcp_pdf/mixins_official/document_assembly.py
mcp_pdf/mixins_official/form_management.py
mcp_pdf/mixins_official/image_processing.py
mcp_pdf/mixins_official/misc_tools.py
mcp_pdf/mixins_official/pdf_utilities.py
mcp_pdf/mixins_official/security_analysis.py
mcp_pdf/mixins_official/table_extraction.py
mcp_pdf/mixins_official/text_extraction.py
mcp_pdf/mixins_official/utils.py
mcp_pdf-2.0.7.dist-info/METADATA
mcp_pdf-2.0.7.dist-info/WHEEL
mcp_pdf-2.0.7.dist-info/entry_points.txt
mcp_pdf-2.0.7.dist-info/licenses/LICENSE
mcp_pdf-2.0.7.dist-info/RECORD
