Metadata-Version: 2.4
Name: mcp-pdf
Version: 2.0.7
Summary: Secure FastMCP server for comprehensive PDF processing - text extraction, OCR, table extraction, forms, annotations, and more
Project-URL: Homepage, https://github.com/rsp2k/mcp-pdf
Project-URL: Documentation, https://github.com/rsp2k/mcp-pdf#readme
Project-URL: Repository, https://github.com/rsp2k/mcp-pdf.git
Project-URL: Issues, https://github.com/rsp2k/mcp-pdf/issues
Project-URL: Changelog, https://github.com/rsp2k/mcp-pdf/releases
Author-email: Ryan Malloy <ryan@malloys.us>
License: MIT
License-File: LICENSE
Keywords: api,fastmcp,integration,mcp,ocr,pdf,pdf-processing,table-extraction,text-extraction
Classifier: Development Status :: 4 - Beta
Classifier: Intended Audience :: Developers
Classifier: License :: OSI Approved :: MIT License
Classifier: Programming Language :: Python :: 3
Classifier: Programming Language :: Python :: 3.10
Classifier: Programming Language :: Python :: 3.11
Classifier: Programming Language :: Python :: 3.12
Classifier: Topic :: Office/Business
Classifier: Topic :: Software Development :: Libraries :: Python Modules
Classifier: Topic :: Text Processing :: General
Requires-Python: >=3.10
Requires-Dist: camelot-py[cv]>=0.11.0
Requires-Dist: fastmcp>=0.1.0
Requires-Dist: httpx>=0.25.0
Requires-Dist: markdown>=3.5.0
Requires-Dist: pandas>=2.0.0
Requires-Dist: pdf2image>=1.16.0
Requires-Dist: pdfplumber>=0.10.0
Requires-Dist: pillow>=10.0.0
Requires-Dist: pydantic>=2.0.0
Requires-Dist: pymupdf>=1.23.0
Requires-Dist: pypdf>=6.0.0
Requires-Dist: pytesseract>=0.3.10
Requires-Dist: python-dotenv>=1.0.0
Requires-Dist: tabula-py>=2.8.0
Provides-Extra: all
Requires-Dist: reportlab>=4.0.0; extra == 'all'
Provides-Extra: dev
Requires-Dist: black>=23.0.0; extra == 'dev'
Requires-Dist: build>=0.10.0; extra == 'dev'
Requires-Dist: mypy>=1.0.0; extra == 'dev'
Requires-Dist: pip-audit>=2.0.0; extra == 'dev'
Requires-Dist: pytest-asyncio>=0.21.0; extra == 'dev'
Requires-Dist: pytest>=7.0.0; extra == 'dev'
Requires-Dist: ruff>=0.1.0; extra == 'dev'
Requires-Dist: safety>=3.0.0; extra == 'dev'
Requires-Dist: twine>=4.0.0; extra == 'dev'
Provides-Extra: forms
Requires-Dist: reportlab>=4.0.0; extra == 'forms'
